MANIFEST.in
Readme.md
setup.py
look_at_me/__init__.py
look_at_me/__version__.py
look_at_me.egg-info/PKG-INFO
look_at_me.egg-info/SOURCES.txt
look_at_me.egg-info/dependency_links.txt
look_at_me.egg-info/entry_points.txt
look_at_me.egg-info/requires.txt
look_at_me.egg-info/top_level.txt
look_at_me/gateway/__init__.py
look_at_me/gateway/app.py
look_at_me/gateway/static/js/highcharts-exporting.js
look_at_me/gateway/static/js/highcharts.js
look_at_me/gateway/static/js/jquery-2.1.3.min.js
look_at_me/gateway/static/js/socket-io.js
look_at_me/gateway/templates/index.html
look_at_me/lib/__init__.py
look_at_me/lib/control_me.py
look_at_me/lib/look_at_me.py