Metadata-Version: 1.1
Name: look-at-me
Version: 0.0.0
Summary: Draw your variables and control them, from the browser
Home-page: http://github.com/ice3/look_at_me
Author: ice3
Author-email: UNKNOWN
License: UNKNOWN
Platform: UNKNOWN
Classifier: Programming Language :: Python
Classifier: Development Status :: 1 - Planning
Classifier: License :: OSI Approved
Classifier: Natural Language :: French
Classifier: Operating System :: OS Independent
Classifier: Programming Language :: Python :: 2.7
Classifier: Topic :: Communications
